verilog/mcp3201_driver.sv
//=============================================================================
// Module       : mcp3201_driver
// Description  : MCP3201 12-bit SPI ADC Driver
//                - 50MHz system clock input
//                - 1MHz SPI clock output (50x divider) — 3.3V safe (max ~1.0MHz)
//                - 40kHz continuous sampling rate
//                - SPI Mode 0,0 (CPOL=0, CPHA=0)
//                - 16 SPI clock cycles per conversion
// Target       : Generic FPGA (Verilog-2001 synthesizable)
// Supply       : VDD = 3.3V (see docs/TIMING_MCP3201_3V3.md)
// Author       : FPGA Design Engineer
// Date         : 2024
//=============================================================================

module mcp3201_driver (
    input  wire       clk,           // 50MHz system clock
    input  wire       rst_n,         // Active-low asynchronous reset

    // ADC SPI interface
    output reg        adc_cs,        // ADC chip select, active low
    output reg        adc_clk,       // ADC SPI clock (1MHz max)
    input  wire       adc_data,      // ADC serial data output (MISO)

    // Sample data output
    output reg  [11:0] sample_data,  // 12-bit ADC conversion result
    output reg         sample_valid, // Data valid flag (1 clk pulse when new data ready)
    output reg         sample_busy   // Conversion in progress flag
);

    //=========================================================================
    // Parameter Definitions
    //=========================================================================
    // System and timing parameters (adjustable for different clock rates)
    // 3.3V supply: fCLK(max) ≈ 1.0 MHz (datasheet: 0.8MHz@2.7V, 1.6MHz@5V)
    parameter CLK_FREQ        = 50_000_000;   // System clock: 50 MHz
    parameter SPI_CLK_FREQ    = 1_000_000;    // SPI clock: 1 MHz (conservative for 3.3V)
    parameter SAMPLE_RATE     = 40_000;       // Sampling rate: 40 kHz

    // Derived timing constants
    parameter SPI_HALF_PERIOD = CLK_FREQ / SPI_CLK_FREQ / 2;  // 25 (50MHz->1MHz)
    parameter SPI_FULL_PERIOD = SPI_HALF_PERIOD * 2;          // 50 clocks per SPI cycle
    parameter SAMPLE_INTERVAL = CLK_FREQ / SAMPLE_RATE;       // 1250 (40kHz period)

    // CS setup time delay: tSUCS(min) = 100 ns @ 50 MHz -> 5 clocks
    localparam CS_SETUP_DELAY = 5;

    //=========================================================================
    // Local State Definitions
    //=========================================================================
    // Four-state FSM: IDLE -> CS_SETUP -> READING -> DONE -> IDLE
    localparam STATE_IDLE     = 2'b00;   // Waiting for next 40kHz tick
    localparam STATE_CS_SETUP = 2'b01;   // CS low before first rising SCLK edge
    localparam STATE_READING  = 2'b10;   // SPI communication in progress
    localparam STATE_DONE     = 2'b11;   // Conversion complete, output data

    localparam TOTAL_SPI_CLKS = 16;
    localparam LAST_SPI_CLK   = TOTAL_SPI_CLKS - 1;
    localparam FIRST_DATA_CLK = 3;       // 4th rising edge: B11
    localparam LAST_DATA_CLK  = 14;      // 15th rising edge: B0

    //=========================================================================
    // Internal Registers
    //=========================================================================
    reg [1:0]  state;              // Current FSM state
    reg [10:0] tick_cnt;           // 40kHz tick counter (0 ~ SAMPLE_INTERVAL-1)
                                   // Free-running at 50MHz, wraps every 1250 clocks
    reg [5:0]  setup_cnt;          // CS setup counter before the first SPI clock
    reg [5:0]  spi_div_cnt;        // SPI clock divider (0 ~ SPI_FULL_PERIOD-1)
                                   // Divides 50MHz to 1MHz (50:1 ratio)
    reg [4:0]  bit_cnt;            // SPI rising-edge counter (0 ~ 15)
                                   // MCP3201 16-clock frame sampled on rising edges:
                                   //   bit 0~1:  DOUT hi-Z, ignore
                                   //   bit 2:    NULL bit, ignore
                                   //   bit 3~14: 12-bit ADC data B11~B0 (MSB first)
                                   //   bit 15:   LSB-first repeated B1, ignore
    reg [11:0] data_buf;           // 12-bit data buffer for collecting ADC result

    //=========================================================================
    // FSM + Timing Control - Main Sequential Logic
    //=========================================================================
    always @(posedge clk or negedge rst_n) begin
        if (!rst_n) begin
            // Reset all registers to known state
            state       <= STATE_IDLE;
            tick_cnt    <= 11'd0;
            setup_cnt   <= 6'd0;
            spi_div_cnt <= 6'd0;
            bit_cnt     <= 5'd0;
            data_buf    <= 12'd0;
            adc_cs      <= 1'b1;       // CS inactive (high)
            adc_clk     <= 1'b0;       // SPI clock idle low for Mode 0,0
            sample_data <= 12'd0;
            sample_valid<= 1'b0;
            sample_busy <= 1'b0;
        end else begin
            //---------------------------------------------------------------
            // Free-running 40kHz tick counter
            // Wraps every SAMPLE_INTERVAL (1250) clocks @ 50MHz
            // This ensures precise 40kHz sampling rate regardless of
            // conversion time (as long as conversion < 1250 clocks)
            // 16 SPI cycles x 50 + CS setup = ~805 clocks < 1250, so timing is safe
            //---------------------------------------------------------------
            tick_cnt <= (tick_cnt >= SAMPLE_INTERVAL - 1) ? 11'd0 : tick_cnt + 1'b1;

            //---------------------------------------------------------------
            // State Machine
            //---------------------------------------------------------------
            case (state)

                //===========================================================
                // STATE_IDLE: Wait for next 40kHz sampling tick
                // ADC_CS is high (inactive), ADC_CLK is low (idle)
                //===========================================================
                STATE_IDLE: begin
                    adc_cs       <= 1'b1;
                    adc_clk      <= 1'b0;
                    sample_valid <= 1'b0;
                    sample_busy  <= 1'b0;

                    // At tick_cnt==0, initiate a new ADC conversion
                    // This triggers exactly every 1250 clocks = 40kHz
                    if (tick_cnt == 11'd0) begin
                        state       <= STATE_CS_SETUP;
                        adc_cs      <= 1'b0;         // Pull CS low to start conversion
                        adc_clk     <= 1'b0;         // Keep CLK low initially to meet
                                                     // tSUCS (CS setup) >= 100 ns
                        setup_cnt   <= 6'd0;
                        spi_div_cnt <= 6'd0;
                        bit_cnt     <= 5'd0;
                        data_buf    <= 12'd0;
                        sample_busy <= 1'b1;
                    end
                end

                //===========================================================
                // STATE_CS_SETUP: Hold CS low before the first SCLK rising edge
                //===========================================================
                STATE_CS_SETUP: begin
                    adc_cs       <= 1'b0;
                    adc_clk      <= 1'b0;
                    sample_valid <= 1'b0;
                    sample_busy  <= 1'b1;

                    if (setup_cnt >= CS_SETUP_DELAY - 1) begin
                        state       <= STATE_READING;
                        setup_cnt   <= 6'd0;
                        spi_div_cnt <= 6'd0;
                        bit_cnt     <= 5'd0;
                    end else begin
                        setup_cnt <= setup_cnt + 1'b1;
                    end
                end

                //===========================================================
                // STATE_READING: SPI communication with MCP3201
                // Generate 1MHz SPI clock and sample data on rising edges
                //===========================================================
                STATE_READING: begin
                    //--- SPI Clock Generation (1MHz from 50MHz) ---
                    // adc_clk rises at spi_div_cnt == 0 and falls at SPI_HALF_PERIOD.
                    if (spi_div_cnt == 6'd0)
                        adc_clk <= 1'b1;
                    else if (spi_div_cnt == SPI_HALF_PERIOD)
                        adc_clk <= 1'b0;

                    //--- Data Sampling on Rising Edge ---
                    // MCP3201 updates DOUT on CLK falling edges; the FPGA samples the
                    // stable value on the following CLK rising edge.
                    if (spi_div_cnt == 6'd0) begin
                        // Capture B11..B0 on rising edges 4 through 15.
                        // Store B11 at data_buf[11], B10 at data_buf[10], ..., B0 at data_buf[0]
                        if (bit_cnt >= FIRST_DATA_CLK && bit_cnt <= LAST_DATA_CLK) begin
                            data_buf[LAST_DATA_CLK - bit_cnt] <= adc_data;
                        end
                    end

                    //--- SPI Clock Divider Counter ---
                    // Count from 0 to SPI_FULL_PERIOD-1 (0 to 49)
                    if (spi_div_cnt >= SPI_FULL_PERIOD - 1) begin
                        // One complete SPI clock cycle done
                        spi_div_cnt <= 6'd0;

                        // After 16 SPI clock cycles (bit_cnt 0~15), conversion is complete
                        if (bit_cnt >= LAST_SPI_CLK) begin
                            state <= STATE_DONE;
                        end else begin
                            bit_cnt <= bit_cnt + 1'b1;
                        end
                    end else begin
                        spi_div_cnt <= spi_div_cnt + 1'b1;
                    end
                end

                //===========================================================
                // STATE_DONE: Conversion complete, latch output data
                // Deassert CS, pulse sample_valid, return to IDLE
                //===========================================================
                STATE_DONE: begin
                    adc_cs       <= 1'b1;          // Deactivate chip select
                    adc_clk      <= 1'b0;          // Return SPI clock to idle (low)
                    sample_data  <= data_buf;      // Output the 12-bit conversion result
                    sample_valid <= 1'b1;          // Pulse data valid flag (1 clock cycle)
                    sample_busy  <= 1'b0;          // Clear busy flag
                    state        <= STATE_IDLE;    // Return to IDLE for next cycle
                end

                //===========================================================
                // Default: Safety fallback to IDLE
                //===========================================================
                default: begin
                    state   <= STATE_IDLE;
                    adc_cs  <= 1'b1;
                    adc_clk <= 1'b0;
                end

            endcase
        end
    end

endmodule

verilog/tb_mcp3201_driver.sv
`timescale 1ns / 1ps

module tb_mcp3201_driver;
    localparam [11:0] ADC_CODE = 12'hA5C;

    reg clk = 1'b0;
    reg rst_n = 1'b0;

    wire adc_cs;
    wire adc_clk;
    tri  adc_data;
    reg  adc_data_drv = 1'bz;

    wire [11:0] sample_data;
    wire        sample_valid;
    wire        sample_busy;

    integer rise_count = 0;
    integer last_rise_count = 0;
    integer fall_count = 0;

    assign adc_data = adc_data_drv;

    always #10 clk = ~clk;

    mcp3201_driver u_dut (
        .clk          (clk),
        .rst_n        (rst_n),
        .adc_cs       (adc_cs),
        .adc_clk      (adc_clk),
        .adc_data     (adc_data),
        .sample_data  (sample_data),
        .sample_valid (sample_valid),
        .sample_busy  (sample_busy)
    );

    always @(negedge adc_cs) begin
        rise_count  = 0;
        fall_count  = 0;
        adc_data_drv = 1'bz;
    end

    always @(posedge adc_clk) begin
        if (!adc_cs)
            rise_count = rise_count + 1;
    end

    always @(posedge adc_cs) begin
        last_rise_count = rise_count;
        adc_data_drv = 1'bz;
    end

    always @(negedge adc_clk) begin
        if (!adc_cs) begin
            fall_count = fall_count + 1;
            case (fall_count)
                1:  adc_data_drv = 1'bz;
                2:  adc_data_drv = 1'b0;
                3:  adc_data_drv = ADC_CODE[11];
                4:  adc_data_drv = ADC_CODE[10];
                5:  adc_data_drv = ADC_CODE[9];
                6:  adc_data_drv = ADC_CODE[8];
                7:  adc_data_drv = ADC_CODE[7];
                8:  adc_data_drv = ADC_CODE[6];
                9:  adc_data_drv = ADC_CODE[5];
                10: adc_data_drv = ADC_CODE[4];
                11: adc_data_drv = ADC_CODE[3];
                12: adc_data_drv = ADC_CODE[2];
                13: adc_data_drv = ADC_CODE[1];
                14: adc_data_drv = ADC_CODE[0];
                15: adc_data_drv = ADC_CODE[1];
                default: adc_data_drv = 1'b0;
            endcase
        end
    end

    always @(posedge clk) begin
        if (sample_valid) begin
            #1;
            if (sample_data !== ADC_CODE) begin
                $display("FAIL: sample_data=%03h expected=%03h", sample_data, ADC_CODE);
                $finish;
            end
            if (last_rise_count != 16) begin
                $display("FAIL: adc_clk rising edges=%0d expected=16", last_rise_count);
                $finish;
            end
            $display("PASS: sample_data=%03h adc_clk rising edges=%0d", sample_data, last_rise_count);
            $finish;
        end
    end

    initial begin
        $dumpfile("tb_mcp3201_driver.vcd");
        $dumpvars(0, tb_mcp3201_driver);

        repeat (5) @(posedge clk);
        rst_n = 1'b1;
    end

    initial begin
        #100000;
        $display("FAIL: timeout");
        $finish;
    end
endmodule

tb_mcp3201_driver.vcd
$date
	Wed May 06 18:06:08 2026
$end
$version
	Icarus Verilog
$end
$timescale
	1ps
$end
$scope module tb_mcp3201_driver $end
$var wire 1 ! adc_data $end
$var wire 1 " sample_valid $end
$var wire 12 # sample_data [11:0] $end
$var wire 1 $ sample_busy $end
$var wire 1 % adc_cs $end
$var wire 1 & adc_clk $end
$var parameter 12 ' ADC_CODE $end
$var reg 1 ( adc_data_drv $end
$var reg 1 ) clk $end
$var reg 1 * rst_n $end
$var integer 32 + fall_count [31:0] $end
$var integer 32 , last_rise_count [31:0] $end
$var integer 32 - rise_count [31:0] $end
$scope module u_dut $end
$var wire 1 ! adc_data $end
$var wire 1 ) clk $end
$var wire 1 * rst_n $end
$var parameter 32 . CLK_FREQ $end
$var parameter 32 / CS_SETUP_DELAY $end
$var parameter 32 0 FIRST_DATA_CLK $end
$var parameter 32 1 LAST_DATA_CLK $end
$var parameter 33 2 LAST_SPI_CLK $end
$var parameter 32 3 SAMPLE_INTERVAL $end
$var parameter 32 4 SAMPLE_RATE $end
$var parameter 32 5 SPI_CLK_FREQ $end
$var parameter 64 6 SPI_FULL_PERIOD $end
$var parameter 32 7 SPI_HALF_PERIOD $end
$var parameter 2 8 STATE_CS_SETUP $end
$var parameter 2 9 STATE_DONE $end
$var parameter 2 : STATE_IDLE $end
$var parameter 2 ; STATE_READING $end
$var parameter 32 < TOTAL_SPI_CLKS $end
$var reg 1 & adc_clk $end
$var reg 1 % adc_cs $end
$var reg 5 = bit_cnt [4:0] $end
$var reg 12 > data_buf [11:0] $end
$var reg 1 $ sample_busy $end
$var reg 12 ? sample_data [11:0] $end
$var reg 1 " sample_valid $end
$var reg 6 @ setup_cnt [5:0] $end
$var reg 6 A spi_div_cnt [5:0] $end
$var reg 2 B state [1:0] $end
$var reg 11 C tick_cnt [10:0] $end
$upscope $end
$upscope $end
$enddefinitions $end
$comment Show the parameter values. $end
$dumpall
b10000 <
b10 ;
b0 :
b11 9
b1 8
b11001 7
b110010 6
b11110100001001000000 5
b1001110001000000 4
b10011100010 3
b1111 2
b1110 1
b11 0
b101 /
b10111110101111000010000000 .
b101001011100 '
$end
#0
$dumpvars
bx C
bx B
bx A
bx @
bx ?
bx >
bx =
b0 -
b0 ,
b0 +
0*
0)
z(
x&
x%
x$
bx #
x"
z!
$end
#10000
0$
0"
b0 #
b0 ?
0&
1%
b0 >
b0 =
b0 A
b0 @
b0 C
b0 B
1)
#20000
0)
#30000
1)
#40000
0)
#50000
1)
#60000
0)
#70000
1)
#80000
0)
#90000
1$
0%
b1 B
b1 C
1*
1)
#100000
0)
#110000
b1 @
b10 C
1)
#120000
0)
#130000
b10 @
b11 C
1)
#140000
0)
#150000
b11 @
b100 C
1)
#160000
0)
#170000
b100 @
b101 C
1)
#180000
0)
#190000
b0 @
b10 B
b110 C
1)
#200000
0)
#210000
b1 -
b1 A
1&
b111 C
1)
#220000
0)
#230000
b10 A
b1000 C
1)
#240000
0)
#250000
b11 A
b1001 C
1)
#260000
0)
#270000
b100 A
b1010 C
1)
#280000
0)
#290000
b101 A
b1011 C
1)
#300000
0)
#310000
b110 A
b1100 C
1)
#320000
0)
#330000
b111 A
b1101 C
1)
#340000
0)
#350000
b1000 A
b1110 C
1)
#360000
0)
#370000
b1001 A
b1111 C
1)
#380000
0)
#390000
b1010 A
b10000 C
1)
#400000
0)
#410000
b1011 A
b10001 C
1)
#420000
0)
#430000
b1100 A
b10010 C
1)
#440000
0)
#450000
b1101 A
b10011 C
1)
#460000
0)
#470000
b1110 A
b10100 C
1)
#480000
0)
#490000
b1111 A
b10101 C
1)
#500000
0)
#510000
b10000 A
b10110 C
1)
#520000
0)
#530000
b10001 A
b10111 C
1)
#540000
0)
#550000
b10010 A
b11000 C
1)
#560000
0)
#570000
b10011 A
b11001 C
1)
#580000
0)
#590000
b10100 A
b11010 C
1)
#600000
0)
#610000
b10101 A
b11011 C
1)
#620000
0)
#630000
b10110 A
b11100 C
1)
#640000
0)
#650000
b10111 A
b11101 C
1)
#660000
0)
#670000
b11000 A
b11110 C
1)
#680000
0)
#690000
b11001 A
b11111 C
1)
#700000
0)
#710000
b1 +
b11010 A
0&
b100000 C
1)
#720000
0)
#730000
b11011 A
b100001 C
1)
#740000
0)
#750000
b11100 A
b100010 C
1)
#760000
0)
#770000
b11101 A
b100011 C
1)
#780000
0)
#790000
b11110 A
b100100 C
1)
#800000
0)
#810000
b11111 A
b100101 C
1)
#820000
0)
#830000
b100000 A
b100110 C
1)
#840000
0)
#850000
b100001 A
b100111 C
1)
#860000
0)
#870000
b100010 A
b101000 C
1)
#880000
0)
#890000
b100011 A
b101001 C
1)
#900000
0)
#910000
b100100 A
b101010 C
1)
#920000
0)
#930000
b100101 A
b101011 C
1)
#940000
0)
#950000
b100110 A
b101100 C
1)
#960000
0)
#970000
b100111 A
b101101 C
1)
#980000
0)
#990000
b101000 A
b101110 C
1)
#1000000
0)
#1010000
b101001 A
b101111 C
1)
#1020000
0)
#1030000
b101010 A
b110000 C
1)
#1040000
0)
#1050000
b101011 A
b110001 C
1)
#1060000
0)
#1070000
b101100 A
b110010 C
1)
#1080000
0)
#1090000
b101101 A
b110011 C
1)
#1100000
0)
#1110000
b101110 A
b110100 C
1)
#1120000
0)
#1130000
b101111 A
b110101 C
1)
#1140000
0)
#1150000
b110000 A
b110110 C
1)
#1160000
0)
#1170000
b110001 A
b110111 C
1)
#1180000
0)
#1190000
b1 =
b0 A
b111000 C
1)
#1200000
0)
#1210000
b10 -
b1 A
1&
b111001 C
1)
#1220000
0)
#1230000
b10 A
b111010 C
1)
#1240000
0)
#1250000
b11 A
b111011 C
1)
#1260000
0)
#1270000
b100 A
b111100 C
1)
#1280000
0)
#1290000
b101 A
b111101 C
1)
#1300000
0)
#1310000
b110 A
b111110 C
1)
#1320000
0)
#1330000
b111 A
b111111 C
1)
#1340000
0)
#1350000
b1000 A
b1000000 C
1)
#1360000
0)
#1370000
b1001 A
b1000001 C
1)
#1380000
0)
#1390000
b1010 A
b1000010 C
1)
#1400000
0)
#1410000
b1011 A
b1000011 C
1)
#1420000
0)
#1430000
b1100 A
b1000100 C
1)
#1440000
0)
#1450000
b1101 A
b1000101 C
1)
#1460000
0)
#1470000
b1110 A
b1000110 C
1)
#1480000
0)
#1490000
b1111 A
b1000111 C
1)
#1500000
0)
#1510000
b10000 A
b1001000 C
1)
#1520000
0)
#1530000
b10001 A
b1001001 C
1)
#1540000
0)
#1550000
b10010 A
b1001010 C
1)
#1560000
0)
#1570000
b10011 A
b1001011 C
1)
#1580000
0)
#1590000
b10100 A
b1001100 C
1)
#1600000
0)
#1610000
b10101 A
b1001101 C
1)
#1620000
0)
#1630000
b10110 A
b1001110 C
1)
#1640000
0)
#1650000
b10111 A
b1001111 C
1)
#1660000
0)
#1670000
b11000 A
b1010000 C
1)
#1680000
0)
#1690000
b11001 A
b1010001 C
1)
#1700000
0)
#1710000
0!
0(
b10 +
b11010 A
0&
b1010010 C
1)
#1720000
0)
#1730000
b11011 A
b1010011 C
1)
#1740000
0)
#1750000
b11100 A
b1010100 C
1)
#1760000
0)
#1770000
b11101 A
b1010101 C
1)
#1780000
0)
#1790000
b11110 A
b1010110 C
1)
#1800000
0)
#1810000
b11111 A
b1010111 C
1)
#1820000
0)
#1830000
b100000 A
b1011000 C
1)
#1840000
0)
#1850000
b100001 A
b1011001 C
1)
#1860000
0)
#1870000
b100010 A
b1011010 C
1)
#1880000
0)
#1890000
b100011 A
b1011011 C
1)
#1900000
0)
#1910000
b100100 A
b1011100 C
1)
#1920000
0)
#1930000
b100101 A
b1011101 C
1)
#1940000
0)
#1950000
b100110 A
b1011110 C
1)
#1960000
0)
#1970000
b100111 A
b1011111 C
1)
#1980000
0)
#1990000
b101000 A
b1100000 C
1)
#2000000
0)
#2010000
b101001 A
b1100001 C
1)
#2020000
0)
#2030000
b101010 A
b1100010 C
1)
#2040000
0)
#2050000
b101011 A
b1100011 C
1)
#2060000
0)
#2070000
b101100 A
b1100100 C
1)
#2080000
0)
#2090000
b101101 A
b1100101 C
1)
#2100000
0)
#2110000
b101110 A
b1100110 C
1)
#2120000
0)
#2130000
b101111 A
b1100111 C
1)
#2140000
0)
#2150000
b110000 A
b1101000 C
1)
#2160000
0)
#2170000
b110001 A
b1101001 C
1)
#2180000
0)
#2190000
b10 =
b0 A
b1101010 C
1)
#2200000
0)
#2210000
b11 -
b1 A
1&
b1101011 C
1)
#2220000
0)
#2230000
b10 A
b1101100 C
1)
#2240000
0)
#2250000
b11 A
b1101101 C
1)
#2260000
0)
#2270000
b100 A
b1101110 C
1)
#2280000
0)
#2290000
b101 A
b1101111 C
1)
#2300000
0)
#2310000
b110 A
b1110000 C
1)
#2320000
0)
#2330000
b111 A
b1110001 C
1)
#2340000
0)
#2350000
b1000 A
b1110010 C
1)
#2360000
0)
#2370000
b1001 A
b1110011 C
1)
#2380000
0)
#2390000
b1010 A
b1110100 C
1)
#2400000
0)
#2410000
b1011 A
b1110101 C
1)
#2420000
0)
#2430000
b1100 A
b1110110 C
1)
#2440000
0)
#2450000
b1101 A
b1110111 C
1)
#2460000
0)
#2470000
b1110 A
b1111000 C
1)
#2480000
0)
#2490000
b1111 A
b1111001 C
1)
#2500000
0)
#2510000
b10000 A
b1111010 C
1)
#2520000
0)
#2530000
b10001 A
b1111011 C
1)
#2540000
0)
#2550000
b10010 A
b1111100 C
1)
#2560000
0)
#2570000
b10011 A
b1111101 C
1)
#2580000
0)
#2590000
b10100 A
b1111110 C
1)
#2600000
0)
#2610000
b10101 A
b1111111 C
1)
#2620000
0)
#2630000
b10110 A
b10000000 C
1)
#2640000
0)
#2650000
b10111 A
b10000001 C
1)
#2660000
0)
#2670000
b11000 A
b10000010 C
1)
#2680000
0)
#2690000
b11001 A
b10000011 C
1)
#2700000
0)
#2710000
1!
1(
b11 +
b11010 A
0&
b10000100 C
1)
#2720000
0)
#2730000
b11011 A
b10000101 C
1)
#2740000
0)
#2750000
b11100 A
b10000110 C
1)
#2760000
0)
#2770000
b11101 A
b10000111 C
1)
#2780000
0)
#2790000
b11110 A
b10001000 C
1)
#2800000
0)
#2810000
b11111 A
b10001001 C
1)
#2820000
0)
#2830000
b100000 A
b10001010 C
1)
#2840000
0)
#2850000
b100001 A
b10001011 C
1)
#2860000
0)
#2870000
b100010 A
b10001100 C
1)
#2880000
0)
#2890000
b100011 A
b10001101 C
1)
#2900000
0)
#2910000
b100100 A
b10001110 C
1)
#2920000
0)
#2930000
b100101 A
b10001111 C
1)
#2940000
0)
#2950000
b100110 A
b10010000 C
1)
#2960000
0)
#2970000
b100111 A
b10010001 C
1)
#2980000
0)
#2990000
b101000 A
b10010010 C
1)
#3000000
0)
#3010000
b101001 A
b10010011 C
1)
#3020000
0)
#3030000
b101010 A
b10010100 C
1)
#3040000
0)
#3050000
b101011 A
b10010101 C
1)
#3060000
0)
#3070000
b101100 A
b10010110 C
1)
#3080000
0)
#3090000
b101101 A
b10010111 C
1)
#3100000
0)
#3110000
b101110 A
b10011000 C
1)
#3120000
0)
#3130000
b101111 A
b10011001 C
1)
#3140000
0)
#3150000
b110000 A
b10011010 C
1)
#3160000
0)
#3170000
b110001 A
b10011011 C
1)
#3180000
0)
#3190000
b11 =
b0 A
b10011100 C
1)
#3200000
0)
#3210000
b100 -
b1 A
b100000000000 >
1&
b10011101 C
1)
#3220000
0)
#3230000
b10 A
b10011110 C
1)
#3240000
0)
#3250000
b11 A
b10011111 C
1)
#3260000
0)
#3270000
b100 A
b10100000 C
1)
#3280000
0)
#3290000
b101 A
b10100001 C
1)
#3300000
0)
#3310000
b110 A
b10100010 C
1)
#3320000
0)
#3330000
b111 A
b10100011 C
1)
#3340000
0)
#3350000
b1000 A
b10100100 C
1)
#3360000
0)
#3370000
b1001 A
b10100101 C
1)
#3380000
0)
#3390000
b1010 A
b10100110 C
1)
#3400000
0)
#3410000
b1011 A
b10100111 C
1)
#3420000
0)
#3430000
b1100 A
b10101000 C
1)
#3440000
0)
#3450000
b1101 A
b10101001 C
1)
#3460000
0)
#3470000
b1110 A
b10101010 C
1)
#3480000
0)
#3490000
b1111 A
b10101011 C
1)
#3500000
0)
#3510000
b10000 A
b10101100 C
1)
#3520000
0)
#3530000
b10001 A
b10101101 C
1)
#3540000
0)
#3550000
b10010 A
b10101110 C
1)
#3560000
0)
#3570000
b10011 A
b10101111 C
1)
#3580000
0)
#3590000
b10100 A
b10110000 C
1)
#3600000
0)
#3610000
b10101 A
b10110001 C
1)
#3620000
0)
#3630000
b10110 A
b10110010 C
1)
#3640000
0)
#3650000
b10111 A
b10110011 C
1)
#3660000
0)
#3670000
b11000 A
b10110100 C
1)
#3680000
0)
#3690000
b11001 A
b10110101 C
1)
#3700000
0)
#3710000
0!
0(
b100 +
b11010 A
0&
b10110110 C
1)
#3720000
0)
#3730000
b11011 A
b10110111 C
1)
#3740000
0)
#3750000
b11100 A
b10111000 C
1)
#3760000
0)
#3770000
b11101 A
b10111001 C
1)
#3780000
0)
#3790000
b11110 A
b10111010 C
1)
#3800000
0)
#3810000
b11111 A
b10111011 C
1)
#3820000
0)
#3830000
b100000 A
b10111100 C
1)
#3840000
0)
#3850000
b100001 A
b10111101 C
1)
#3860000
0)
#3870000
b100010 A
b10111110 C
1)
#3880000
0)
#3890000
b100011 A
b10111111 C
1)
#3900000
0)
#3910000
b100100 A
b11000000 C
1)
#3920000
0)
#3930000
b100101 A
b11000001 C
1)
#3940000
0)
#3950000
b100110 A
b11000010 C
1)
#3960000
0)
#3970000
b100111 A
b11000011 C
1)
#3980000
0)
#3990000
b101000 A
b11000100 C
1)
#4000000
0)
#4010000
b101001 A
b11000101 C
1)
#4020000
0)
#4030000
b101010 A
b11000110 C
1)
#4040000
0)
#4050000
b101011 A
b11000111 C
1)
#4060000
0)
#4070000
b101100 A
b11001000 C
1)
#4080000
0)
#4090000
b101101 A
b11001001 C
1)
#4100000
0)
#4110000
b101110 A
b11001010 C
1)
#4120000
0)
#4130000
b101111 A
b11001011 C
1)
#4140000
0)
#4150000
b110000 A
b11001100 C
1)
#4160000
0)
#4170000
b110001 A
b11001101 C
1)
#4180000
0)
#4190000
b100 =
b0 A
b11001110 C
1)
#4200000
0)
#4210000
b101 -
b1 A
1&
b11001111 C
1)
#4220000
0)
#4230000
b10 A
b11010000 C
1)
#4240000
0)
#4250000
b11 A
b11010001 C
1)
#4260000
0)
#4270000
b100 A
b11010010 C
1)
#4280000
0)
#4290000
b101 A
b11010011 C
1)
#4300000
0)
#4310000
b110 A
b11010100 C
1)
#4320000
0)
#4330000
b111 A
b11010101 C
1)
#4340000
0)
#4350000
b1000 A
b11010110 C
1)
#4360000
0)
#4370000
b1001 A
b11010111 C
1)
#4380000
0)
#4390000
b1010 A
b11011000 C
1)
#4400000
0)
#4410000
b1011 A
b11011001 C
1)
#4420000
0)
#4430000
b1100 A
b11011010 C
1)
#4440000
0)
#4450000
b1101 A
b11011011 C
1)
#4460000
0)
#4470000
b1110 A
b11011100 C
1)
#4480000
0)
#4490000
b1111 A
b11011101 C
1)
#4500000
0)
#4510000
b10000 A
b11011110 C
1)
#4520000
0)
#4530000
b10001 A
b11011111 C
1)
#4540000
0)
#4550000
b10010 A
b11100000 C
1)
#4560000
0)
#4570000
b10011 A
b11100001 C
1)
#4580000
0)
#4590000
b10100 A
b11100010 C
1)
#4600000
0)
#4610000
b10101 A
b11100011 C
1)
#4620000
0)
#4630000
b10110 A
b11100100 C
1)
#4640000
0)
#4650000
b10111 A
b11100101 C
1)
#4660000
0)
#4670000
b11000 A
b11100110 C
1)
#4680000
0)
#4690000
b11001 A
b11100111 C
1)
#4700000
0)
#4710000
1!
1(
b101 +
b11010 A
0&
b11101000 C
1)
#4720000
0)
#4730000
b11011 A
b11101001 C
1)
#4740000
0)
#4750000
b11100 A
b11101010 C
1)
#4760000
0)
#4770000
b11101 A
b11101011 C
1)
#4780000
0)
#4790000
b11110 A
b11101100 C
1)
#4800000
0)
#4810000
b11111 A
b11101101 C
1)
#4820000
0)
#4830000
b100000 A
b11101110 C
1)
#4840000
0)
#4850000
b100001 A
b11101111 C
1)
#4860000
0)
#4870000
b100010 A
b11110000 C
1)
#4880000
0)
#4890000
b100011 A
b11110001 C
1)
#4900000
0)
#4910000
b100100 A
b11110010 C
1)
#4920000
0)
#4930000
b100101 A
b11110011 C
1)
#4940000
0)
#4950000
b100110 A
b11110100 C
1)
#4960000
0)
#4970000
b100111 A
b11110101 C
1)
#4980000
0)
#4990000
b101000 A
b11110110 C
1)
#5000000
0)
#5010000
b101001 A
b11110111 C
1)
#5020000
0)
#5030000
b101010 A
b11111000 C
1)
#5040000
0)
#5050000
b101011 A
b11111001 C
1)
#5060000
0)
#5070000
b101100 A
b11111010 C
1)
#5080000
0)
#5090000
b101101 A
b11111011 C
1)
#5100000
0)
#5110000
b101110 A
b11111100 C
1)
#5120000
0)
#5130000
b101111 A
b11111101 C
1)
#5140000
0)
#5150000
b110000 A
b11111110 C
1)
#5160000
0)
#5170000
b110001 A
b11111111 C
1)
#5180000
0)
#5190000
b101 =
b0 A
b100000000 C
1)
#5200000
0)
#5210000
b110 -
b1 A
b101000000000 >
1&
b100000001 C
1)
#5220000
0)
#5230000
b10 A
b100000010 C
1)
#5240000
0)
#5250000
b11 A
b100000011 C
1)
#5260000
0)
#5270000
b100 A
b100000100 C
1)
#5280000
0)
#5290000
b101 A
b100000101 C
1)
#5300000
0)
#5310000
b110 A
b100000110 C
1)
#5320000
0)
#5330000
b111 A
b100000111 C
1)
#5340000
0)
#5350000
b1000 A
b100001000 C
1)
#5360000
0)
#5370000
b1001 A
b100001001 C
1)
#5380000
0)
#5390000
b1010 A
b100001010 C
1)
#5400000
0)
#5410000
b1011 A
b100001011 C
1)
#5420000
0)
#5430000
b1100 A
b100001100 C
1)
#5440000
0)
#5450000
b1101 A
b100001101 C
1)
#5460000
0)
#5470000
b1110 A
b100001110 C
1)
#5480000
0)
#5490000
b1111 A
b100001111 C
1)
#5500000
0)
#5510000
b10000 A
b100010000 C
1)
#5520000
0)
#5530000
b10001 A
b100010001 C
1)
#5540000
0)
#5550000
b10010 A
b100010010 C
1)
#5560000
0)
#5570000
b10011 A
b100010011 C
1)
#5580000
0)
#5590000
b10100 A
b100010100 C
1)
#5600000
0)
#5610000
b10101 A
b100010101 C
1)
#5620000
0)
#5630000
b10110 A
b100010110 C
1)
#5640000
0)
#5650000
b10111 A
b100010111 C
1)
#5660000
0)
#5670000
b11000 A
b100011000 C
1)
#5680000
0)
#5690000
b11001 A
b100011001 C
1)
#5700000
0)
#5710000
0!
0(
b110 +
b11010 A
0&
b100011010 C
1)
#5720000
0)
#5730000
b11011 A
b100011011 C
1)
#5740000
0)
#5750000
b11100 A
b100011100 C
1)
#5760000
0)
#5770000
b11101 A
b100011101 C
1)
#5780000
0)
#5790000
b11110 A
b100011110 C
1)
#5800000
0)
#5810000
b11111 A
b100011111 C
1)
#5820000
0)
